{
  "posts": [
    {
      "id": "1",
      "title": "json-server",
      "userId": "1"
    },
    {
      "id": "2",
      "title": "json-server",
      "userId": "2"
    }
  ],
  "comments": [
    {
      "id": "1",
      "body": "some comment",
      "postId": "1"
    }
  ],
  "users": [
    {
      "id": "1",
      "username": "admin",
      "password": "123"
    }
  ],
  "profile": {
    "first": "Денис",
    "lastname": "Стукало",
    "age": 23,
    "currency": "RUB",
    "country": "Russia",
    "city": "St. Petersburg",
    "username": "admin",
    "avatar": "https://png.klev.club/uploads/posts/2024-04/png-klev-club-v3lo-p-avatarka-png-2.png"
  }
}